ashpool/__init__.py
ashpool/ashpool.py
ashpool/dummy.py
ashpool/tests/__init__.py
ashpool/tests/test_ashpool.py
ashpool-0.2.1.dist-info/DESCRIPTION.rst
ashpool-0.2.1.dist-info/METADATA
ashpool-0.2.1.dist-info/RECORD
ashpool-0.2.1.dist-info/WHEEL
ashpool-0.2.1.dist-info/metadata.json
ashpool-0.2.1.dist-info/top_level.txt
