Metadata-Version: 2.0
Name: ashpool
Version: 0.2.1
Summary: A quick and easy way to reconcile two data series.
Home-page: http://github.com/cktc/ashpool
Author: Christopher Cheung
Author-email: chris.kt.cheung@gmail.com
License: MIT
Download-URL: http://github.com/cktc/ashpool/archive/v0.2.1.tar.gz
Keywords: compare pandas dataframes
Platform: UNKNOWN
Classifier: Development Status :: 3 - Alpha
Classifier: License :: OSI Approved :: MIT License
Classifier: Programming Language :: Python :: 2
Classifier: Programming Language :: Python :: 2.7
Classifier: Programming Language :: Python :: 3
Classifier: Programming Language :: Python :: 3.4
Requires-Dist: pandas
Requires-Dist: numpy
Requires-Dist: ipython
Requires-Dist: future
